templatetag_handlebars/__init__.py
templatetag_handlebars/models.py
templatetag_handlebars/tests.py
templatetag_handlebars/static/handlebars.js
templatetag_handlebars/templatetags/__init__.py
templatetag_handlebars/templatetags/templatetag_handlebars.py
django_templatetag_handlebars_new-1.3.2.dev2.dist-info/LICENSE
django_templatetag_handlebars_new-1.3.2.dev2.dist-info/METADATA
django_templatetag_handlebars_new-1.3.2.dev2.dist-info/WHEEL
django_templatetag_handlebars_new-1.3.2.dev2.dist-info/top_level.txt
django_templatetag_handlebars_new-1.3.2.dev2.dist-info/RECORD
