Metadata-Version: 2.1
Name: django-templatetag-handlebars-new
Version: 1.3.2.dev2
Summary: Easily embed Handlebars.js templates in your django templates
Home-page: https://github.com/makinacorpus/django-templatetag-handlebars
Author: Mathieu Leplatre
Author-email: mathieu.leplatre@makina-corpus.com
License: LPGL, see LICENSE file.
Download-URL: http://pypi.python.org/pypi/django-templatetag-handlebars/
Platform: UNKNOWN
Classifier: Topic :: Utilities
Classifier: Natural Language :: English
Classifier: Operating System :: OS Independent
Classifier: Intended Audience :: Developers
Classifier: Environment :: Web Environment
Classifier: Framework :: Django
Classifier: Development Status :: 5 - Production/Stable
Classifier: Programming Language :: Python :: 2.7
Classifier: Programming Language :: Python :: 3.3
License-File: LICENSE
Requires-Dist: django
Requires-Dist: six
